{"df6cbf5b84f7c0abbec6f8e56c48b69b": {"APPID": "sigAlert", "Issuer": "juyao@yaoju", "Commit": "2026-03-28T10:47:37", "TS": 1774709257, "TS_EXP": 1774710757}, "fda471df87099cc81514fba669b58671": {"TS_EXP": 1774709549.0, "Issuer": "root@PI3B_1", "APPID": "Monitor", "Commit": "2026-03-28T10:36:29", "TS": 1774708589}, "5b33203a8dc24f3218812625063190f0": {"TS_EXP": 1774709892, "Issuer": "juyao@YAOJU-SP", "APPID": "sigAlert", "Commit": "2026-03-28T10:33:12", "TS": 1774708392}, "4bfa9b4646193db91c15bfcd76dcaa7a": {"TS_EXP": 1767733717.0, "Issuer": "Jun@JunYao-PC", "APPID": "NEST", "Commit": "2026-01-05T11:20:37", "TS": 1767630037}}